{
  "developer_name": "Кронверк",
  "url": "https://kronverksar.ru/",
  "quarter_id": "2026-Q2",
  "applications": [
    {
      "application_id": "APP-3-016",
      "submitted_at": "2026-06-02T06:48:00.000Z",
      "time_slot": "morning",
      "day_of_week": "tuesday",
      "got_identified_call": false,
      "phone_number": "+7 (930) 925-06-25"
    },
    {
      "application_id": "APP-3-049",
      "submitted_at": "2026-06-02T10:27:00.000Z",
      "time_slot": "afternoon",
      "day_of_week": "tuesday",
      "got_identified_call": false,
      "phone_number": "+7 (930) 954-93-00"
    },
    {
      "application_id": "APP-3-082",
      "submitted_at": "2026-06-02T16:19:59.000Z",
      "time_slot": "evening",
      "day_of_week": "tuesday",
      "got_identified_call": true,
      "phone_number": "+7 (930) 964-06-44"
    },
    {
      "application_id": "APP-3-115",
      "submitted_at": "2026-06-03T06:17:59.000Z",
      "time_slot": "morning",
      "day_of_week": "tuesday",
      "got_identified_call": false,
      "phone_number": "+7 (901) 347-53-59"
    },
    {
      "application_id": "APP-3-148",
      "submitted_at": "2026-06-03T10:25:00.000Z",
      "time_slot": "afternoon",
      "day_of_week": "tuesday",
      "got_identified_call": false,
      "phone_number": "+7 (991) 134-10-86"
    },
    {
      "application_id": "APP-3-181",
      "submitted_at": "2026-06-03T16:22:00.000Z",
      "time_slot": "evening",
      "day_of_week": "tuesday",
      "got_identified_call": false,
      "phone_number": "+7 (991) 238-50-38"
    },
    {
      "application_id": "APP-3-214",
      "submitted_at": "2026-06-04T06:27:00.000Z",
      "time_slot": "morning",
      "day_of_week": "thursday",
      "got_identified_call": false,
      "phone_number": "+7 (903) 586-90-43"
    },
    {
      "application_id": "APP-3-247",
      "submitted_at": "2026-06-04T10:22:00.000Z",
      "time_slot": "afternoon",
      "day_of_week": "thursday",
      "got_identified_call": false,
      "phone_number": "+7 (903) 586-90-53"
    },
    {
      "application_id": "APP-3-280",
      "submitted_at": "2026-06-04T16:33:00.000Z",
      "time_slot": "evening",
      "day_of_week": "thursday",
      "got_identified_call": false,
      "phone_number": "+7 (906) 708-49-29"
    },
    {
      "application_id": "APP-3-313",
      "submitted_at": "2026-06-05T06:33:00.000Z",
      "time_slot": "morning",
      "day_of_week": "friday",
      "got_identified_call": true,
      "phone_number": "+7 (909) 955-34-30"
    },
    {
      "application_id": "APP-3-346",
      "submitted_at": "2026-06-05T10:29:00.000Z",
      "time_slot": "afternoon",
      "day_of_week": "friday",
      "got_identified_call": true,
      "phone_number": "+7 (901) 335-66-79"
    },
    {
      "application_id": "APP-3-379",
      "submitted_at": "2026-06-05T16:43:00.000Z",
      "time_slot": "evening",
      "day_of_week": "friday",
      "got_identified_call": true,
      "phone_number": "+7 (991) 181-01-99"
    },
    {
      "application_id": "APP-3-412",
      "submitted_at": "2026-06-06T06:36:00.000Z",
      "time_slot": "morning",
      "day_of_week": "saturday",
      "got_identified_call": true,
      "phone_number": "+7 (965) 127-47-13"
    },
    {
      "application_id": "APP-3-445",
      "submitted_at": "2026-06-06T11:28:00.000Z",
      "time_slot": "afternoon",
      "day_of_week": "saturday",
      "got_identified_call": true,
      "phone_number": "+7 (903) 964-17-42"
    },
    {
      "application_id": "APP-3-478",
      "submitted_at": "2026-06-06T16:37:00.000Z",
      "time_slot": "evening",
      "day_of_week": "saturday",
      "got_identified_call": true,
      "phone_number": "+7 (965) 127-09-80"
    },
    {
      "application_id": "APP-3-511",
      "submitted_at": "2026-06-07T07:50:00.000Z",
      "time_slot": "morning",
      "day_of_week": "sunday",
      "got_identified_call": true,
      "phone_number": "+7 (903) 673-81-93"
    },
    {
      "application_id": "APP-3-544",
      "submitted_at": "2026-06-07T10:50:00.000Z",
      "time_slot": "afternoon",
      "day_of_week": "sunday",
      "got_identified_call": true,
      "phone_number": "+7 (967) 016-79-41"
    },
    {
      "application_id": "APP-3-577",
      "submitted_at": "2026-06-07T16:18:00.000Z",
      "time_slot": "evening",
      "day_of_week": "sunday",
      "got_identified_call": true,
      "phone_number": "+7 (903) 739-96-34"
    },
    {
      "application_id": "APP-3-610",
      "submitted_at": "2026-06-08T06:16:00.000Z",
      "time_slot": "morning",
      "day_of_week": "monday",
      "got_identified_call": true,
      "phone_number": "+7 (903) 791-55-87"
    },
    {
      "application_id": "APP-3-643",
      "submitted_at": "2026-06-08T10:15:00.000Z",
      "time_slot": "afternoon",
      "day_of_week": "monday",
      "got_identified_call": false,
      "phone_number": "+7 (905) 513-31-09"
    },
    {
      "application_id": "APP-3-676",
      "submitted_at": "2026-06-08T16:18:00.000Z",
      "time_slot": "evening",
      "day_of_week": "monday",
      "got_identified_call": false,
      "phone_number": "+7 (901) 507-47-17"
    }
  ],
  "events": [
    {
      "event_id": "E-M-0004",
      "application_id": "APP-3-016",
      "event_at": "2026-06-02T10:05:00.000Z",
      "minutes_since_application": 197,
      "channel": "max",
      "from_phone": "+7 (927) 130-81-31",
      "identified_status": "developer",
      "verification_confidence": "high"
    },
    {
      "event_id": "E-M-0060",
      "application_id": "APP-3-049",
      "event_at": "2026-06-02T10:45:00.000Z",
      "minutes_since_application": 18,
      "channel": "max",
      "from_phone": "+7 (927) 130-81-31",
      "identified_status": "developer",
      "verification_confidence": "high"
    },
    {
      "event_id": "E-SC-0173",
      "application_id": "APP-3-082",
      "event_at": "2026-06-03T12:27:00.000Z",
      "minutes_since_application": 1207,
      "channel": "sms",
      "from_phone": "GK_Kronverk",
      "identified_status": "developer",
      "verification_confidence": "high",
      "sms_mark": "GK_Kronverk"
    },
    {
      "event_id": "E-SC-0174",
      "application_id": "APP-3-082",
      "event_at": "2026-06-05T12:28:00.000Z",
      "minutes_since_application": 4088,
      "channel": "sms",
      "from_phone": "GK_Kronverk",
      "identified_status": "developer",
      "verification_confidence": "high",
      "sms_mark": "GK_Kronverk"
    },
    {
      "event_id": "E-SC-0175",
      "application_id": "APP-3-313",
      "event_at": "2026-06-08T05:11:00.000Z",
      "minutes_since_application": 4238,
      "channel": "sms",
      "from_phone": "GK_KRONVERK",
      "identified_status": "developer",
      "verification_confidence": "high",
      "sms_mark": "GK_KRONVERK"
    },
    {
      "event_id": "E-SC-0176",
      "application_id": "APP-3-412",
      "event_at": "2026-06-08T05:19:00.000Z",
      "minutes_since_application": 2803,
      "channel": "sms",
      "from_phone": "GK_KRONVERK",
      "identified_status": "developer",
      "verification_confidence": "high",
      "sms_mark": "GK_KRONVERK"
    },
    {
      "event_id": "E-SC-0177",
      "application_id": "APP-3-544",
      "event_at": "2026-06-08T05:20:00.000Z",
      "minutes_since_application": 1110,
      "channel": "sms",
      "from_phone": "GK_KRONVERK",
      "identified_status": "developer",
      "verification_confidence": "high",
      "sms_mark": "GK_KRONVERK"
    },
    {
      "event_id": "E-SC-0178",
      "application_id": "APP-3-577",
      "event_at": "2026-06-08T05:26:00.000Z",
      "minutes_since_application": 788,
      "channel": "sms",
      "from_phone": "GK_KRONVERK",
      "identified_status": "developer",
      "verification_confidence": "high",
      "sms_mark": "GK_KRONVERK"
    },
    {
      "event_id": "E-SC-0179",
      "application_id": "APP-3-445",
      "event_at": "2026-06-08T05:42:00.000Z",
      "minutes_since_application": 2534,
      "channel": "sms",
      "from_phone": "GK_KRONVERK",
      "identified_status": "developer",
      "verification_confidence": "high",
      "sms_mark": "GK_KRONVERK"
    },
    {
      "event_id": "E-SC-0180",
      "application_id": "APP-3-478",
      "event_at": "2026-06-08T05:43:00.000Z",
      "minutes_since_application": 2226,
      "channel": "sms",
      "from_phone": "GK_KRONVERK",
      "identified_status": "developer",
      "verification_confidence": "high",
      "sms_mark": "GK_KRONVERK"
    },
    {
      "event_id": "E-SC-0181",
      "application_id": "APP-3-379",
      "event_at": "2026-06-08T05:44:00.000Z",
      "minutes_since_application": 3661,
      "channel": "sms",
      "from_phone": "GK_Kronverk",
      "identified_status": "developer",
      "verification_confidence": "high",
      "sms_mark": "GK_Kronverk"
    },
    {
      "event_id": "E-SC-0182",
      "application_id": "APP-3-346",
      "event_at": "2026-06-08T05:45:00.000Z",
      "minutes_since_application": 4036,
      "channel": "sms",
      "from_phone": "GK_Kronverk",
      "identified_status": "developer",
      "verification_confidence": "high",
      "sms_mark": "GK_Kronverk"
    },
    {
      "event_id": "E-SC-0183",
      "application_id": "APP-3-511",
      "event_at": "2026-06-08T07:06:00.000Z",
      "minutes_since_application": 1396,
      "channel": "sms",
      "from_phone": "GK_KRONVERK",
      "identified_status": "developer",
      "verification_confidence": "high",
      "sms_mark": "GK_KRONVERK"
    },
    {
      "event_id": "E-SC-0184",
      "application_id": "APP-3-511",
      "event_at": "2026-06-08T08:54:00.000Z",
      "minutes_since_application": 1504,
      "channel": "sms",
      "from_phone": "GK_KRONVERK",
      "identified_status": "developer",
      "verification_confidence": "high",
      "sms_mark": "GK_KRONVERK"
    },
    {
      "event_id": "E-SC-0185",
      "application_id": "APP-3-511",
      "event_at": "2026-06-08T11:55:00.000Z",
      "minutes_since_application": 1685,
      "channel": "sms",
      "from_phone": "GK_KRONVERK",
      "identified_status": "developer",
      "verification_confidence": "high",
      "sms_mark": "GK_KRONVERK"
    },
    {
      "event_id": "E-SC-0186",
      "application_id": "APP-3-511",
      "event_at": "2026-06-08T17:55:00.000Z",
      "minutes_since_application": 2045,
      "channel": "sms",
      "from_phone": "GK_KRONVERK",
      "identified_status": "developer",
      "verification_confidence": "high",
      "sms_mark": "GK_KRONVERK"
    },
    {
      "event_id": "E-SC-0187",
      "application_id": "APP-3-511",
      "event_at": "2026-06-09T05:56:00.000Z",
      "minutes_since_application": 2766,
      "channel": "sms",
      "from_phone": "GK_KRONVERK",
      "identified_status": "developer",
      "verification_confidence": "high",
      "sms_mark": "GK_KRONVERK"
    },
    {
      "event_id": "events_sms_calls-818",
      "application_id": "",
      "event_at": "2026-06-02T07:39:00.000Z",
      "minutes_since_application": null,
      "channel": "call",
      "from_phone": "+7 (845) 233-85-31",
      "identified_status": "developer",
      "verification_confidence": "high"
    },
    {
      "event_id": "events_sms_calls-880",
      "application_id": "",
      "event_at": "2026-06-02T10:01:00.000Z",
      "minutes_since_application": null,
      "channel": "call",
      "from_phone": "+7 (845) 233-85-31",
      "identified_status": "developer",
      "verification_confidence": "high"
    },
    {
      "event_id": "events_sms_calls-934",
      "application_id": "",
      "event_at": "2026-06-02T10:43:00.000Z",
      "minutes_since_application": null,
      "channel": "call",
      "from_phone": "+7 (845) 233-85-31",
      "identified_status": "developer",
      "verification_confidence": "high"
    },
    {
      "event_id": "events_sms_calls-936",
      "application_id": "",
      "event_at": "2026-06-02T10:44:00.000Z",
      "minutes_since_application": null,
      "channel": "call",
      "from_phone": "+7 (845) 233-85-31",
      "identified_status": "developer",
      "verification_confidence": "high"
    },
    {
      "event_id": "events_sms_calls-1522",
      "application_id": "",
      "event_at": "2026-06-03T12:08:00.000Z",
      "minutes_since_application": null,
      "channel": "call",
      "from_phone": "+7 (845) 233-85-31",
      "identified_status": "developer",
      "verification_confidence": "high"
    },
    {
      "event_id": "E-SC-0845",
      "application_id": "APP-3-082",
      "event_at": "2026-06-03T12:26:00.000Z",
      "minutes_since_application": 1206,
      "channel": "call",
      "from_phone": "+7 (845) 233-85-31",
      "identified_status": "developer",
      "verification_confidence": "high"
    },
    {
      "event_id": "events_sms_calls-3118",
      "application_id": "",
      "event_at": "2026-06-05T12:25:00.000Z",
      "minutes_since_application": null,
      "channel": "call",
      "from_phone": "+7 (845) 233-85-31",
      "identified_status": "developer",
      "verification_confidence": "high"
    },
    {
      "event_id": "E-SC-1729",
      "application_id": "APP-3-082",
      "event_at": "2026-06-05T12:28:00.000Z",
      "minutes_since_application": 4088,
      "channel": "call",
      "from_phone": "+7 (845) 233-85-31",
      "identified_status": "developer",
      "verification_confidence": "high"
    },
    {
      "event_id": "E-SC-2400",
      "application_id": "APP-3-313",
      "event_at": "2026-06-08T05:10:00.000Z",
      "minutes_since_application": 4237,
      "channel": "call",
      "from_phone": "+7 (845) 233-85-31",
      "identified_status": "developer",
      "verification_confidence": "high"
    },
    {
      "event_id": "E-SC-2404",
      "application_id": "APP-3-412",
      "event_at": "2026-06-08T05:18:00.000Z",
      "minutes_since_application": 2802,
      "channel": "call",
      "from_phone": "+7 (845) 233-85-31",
      "identified_status": "developer",
      "verification_confidence": "high"
    },
    {
      "event_id": "E-SC-2406",
      "application_id": "APP-3-544",
      "event_at": "2026-06-08T05:20:00.000Z",
      "minutes_since_application": 1110,
      "channel": "call",
      "from_phone": "+7 (845) 233-85-31",
      "identified_status": "developer",
      "verification_confidence": "high"
    },
    {
      "event_id": "E-SC-2408",
      "application_id": "APP-3-577",
      "event_at": "2026-06-08T05:25:00.000Z",
      "minutes_since_application": 787,
      "channel": "call",
      "from_phone": "+7 (845) 233-85-31",
      "identified_status": "developer",
      "verification_confidence": "high"
    },
    {
      "event_id": "E-SC-2417",
      "application_id": "APP-3-445",
      "event_at": "2026-06-08T05:41:00.000Z",
      "minutes_since_application": 2533,
      "channel": "call",
      "from_phone": "+7 (845) 233-85-31",
      "identified_status": "developer",
      "verification_confidence": "high"
    },
    {
      "event_id": "E-SC-2419",
      "application_id": "APP-3-478",
      "event_at": "2026-06-08T05:42:00.000Z",
      "minutes_since_application": 2225,
      "channel": "call",
      "from_phone": "+7 (845) 233-85-31",
      "identified_status": "developer",
      "verification_confidence": "high"
    },
    {
      "event_id": "E-SC-2421",
      "application_id": "APP-3-379",
      "event_at": "2026-06-08T05:44:00.000Z",
      "minutes_since_application": 3661,
      "channel": "call",
      "from_phone": "+7 (845) 233-85-31",
      "identified_status": "developer",
      "verification_confidence": "high"
    },
    {
      "event_id": "E-SC-2424",
      "application_id": "APP-3-346",
      "event_at": "2026-06-08T05:45:00.000Z",
      "minutes_since_application": 4036,
      "channel": "call",
      "from_phone": "+7 (845) 233-85-31",
      "identified_status": "developer",
      "verification_confidence": "high"
    },
    {
      "event_id": "events_sms_calls-4660",
      "application_id": "",
      "event_at": "2026-06-08T05:46:00.000Z",
      "minutes_since_application": null,
      "channel": "call",
      "from_phone": "+7 (845) 233-85-31",
      "identified_status": "developer",
      "verification_confidence": "high"
    },
    {
      "event_id": "events_sms_calls-4794",
      "application_id": "",
      "event_at": "2026-06-08T06:51:00.000Z",
      "minutes_since_application": null,
      "channel": "call",
      "from_phone": "+7 (845) 233-85-31",
      "identified_status": "developer",
      "verification_confidence": "high"
    },
    {
      "event_id": "events_sms_calls-4802",
      "application_id": "",
      "event_at": "2026-06-08T06:55:00.000Z",
      "minutes_since_application": null,
      "channel": "call",
      "from_phone": "+7 (845) 233-85-31",
      "identified_status": "developer",
      "verification_confidence": "high"
    },
    {
      "event_id": "E-SC-2515",
      "application_id": "APP-3-511",
      "event_at": "2026-06-08T07:05:00.000Z",
      "minutes_since_application": 1395,
      "channel": "call",
      "from_phone": "+7 (845) 233-85-31",
      "identified_status": "developer",
      "verification_confidence": "high"
    },
    {
      "event_id": "events_sms_calls-4835",
      "application_id": "",
      "event_at": "2026-06-08T07:15:00.000Z",
      "minutes_since_application": null,
      "channel": "call",
      "from_phone": "+7 (845) 233-85-31",
      "identified_status": "developer",
      "verification_confidence": "high"
    },
    {
      "event_id": "E-SC-2529",
      "application_id": "APP-3-346",
      "event_at": "2026-06-08T07:17:00.000Z",
      "minutes_since_application": 4128,
      "channel": "call",
      "from_phone": "+7 (845) 233-85-31",
      "identified_status": "developer",
      "verification_confidence": "high"
    },
    {
      "event_id": "E-SC-2535",
      "application_id": "APP-3-412",
      "event_at": "2026-06-08T07:19:00.000Z",
      "minutes_since_application": 2923,
      "channel": "call",
      "from_phone": "+7 (845) 233-85-31",
      "identified_status": "developer",
      "verification_confidence": "high"
    },
    {
      "event_id": "E-SC-2540",
      "application_id": "APP-3-544",
      "event_at": "2026-06-08T07:22:00.000Z",
      "minutes_since_application": 1232,
      "channel": "call",
      "from_phone": "+7 (845) 233-85-31",
      "identified_status": "developer",
      "verification_confidence": "high"
    },
    {
      "event_id": "E-SC-2542",
      "application_id": "APP-3-577",
      "event_at": "2026-06-08T07:24:00.000Z",
      "minutes_since_application": 906,
      "channel": "call",
      "from_phone": "+7 (845) 233-85-31",
      "identified_status": "developer",
      "verification_confidence": "high"
    },
    {
      "event_id": "events_sms_calls-4869",
      "application_id": "",
      "event_at": "2026-06-08T07:31:00.000Z",
      "minutes_since_application": null,
      "channel": "call",
      "from_phone": "+7 (845) 233-85-31",
      "identified_status": "developer",
      "verification_confidence": "high"
    },
    {
      "event_id": "E-SC-2630",
      "application_id": "APP-3-478",
      "event_at": "2026-06-08T09:08:00.000Z",
      "minutes_since_application": 2431,
      "channel": "call",
      "from_phone": "+7 (845) 233-85-31",
      "identified_status": "developer",
      "verification_confidence": "high"
    },
    {
      "event_id": "E-SC-2897",
      "application_id": "APP-3-610",
      "event_at": "2026-06-09T07:14:00.000Z",
      "minutes_since_application": 1498,
      "channel": "call",
      "from_phone": "+7 (845) 233-85-31",
      "identified_status": "developer",
      "verification_confidence": "high"
    },
    {
      "event_id": "events_sms_calls-6639",
      "application_id": "",
      "event_at": "2026-06-10T11:42:00.000Z",
      "minutes_since_application": null,
      "channel": "call",
      "from_phone": "+7 (845) 233-85-31",
      "identified_status": "developer",
      "verification_confidence": "high"
    }
  ]
}
