{
  "developer_name": "ТЭН",
  "url": "ten-stroy.ru",
  "quarter_id": "2026-Q2",
  "applications": [
    {
      "application_id": "APP-1-032",
      "submitted_at": "2026-06-02T10:30:00.000Z",
      "time_slot": "morning",
      "day_of_week": "tuesday",
      "got_identified_call": true,
      "phone_number": "+7 (903) 586-90-43"
    },
    {
      "application_id": "APP-1-066",
      "submitted_at": "2026-06-02T13:50:00.000Z",
      "time_slot": "afternoon",
      "day_of_week": "tuesday",
      "got_identified_call": true,
      "phone_number": "+7 (903) 739-96-34"
    },
    {
      "application_id": "APP-1-100",
      "submitted_at": "2026-06-02T22:34:59.999Z",
      "time_slot": "evening",
      "day_of_week": "tuesday",
      "got_identified_call": true,
      "phone_number": "+7 (906) 708-49-29"
    },
    {
      "application_id": "APP-1-134",
      "submitted_at": "2026-06-03T10:15:00.000Z",
      "time_slot": "morning",
      "day_of_week": "wednesday",
      "got_identified_call": true,
      "phone_number": "+7 (909) 955-34-30"
    },
    {
      "application_id": "APP-1-168",
      "submitted_at": "2026-06-03T14:37:00.000Z",
      "time_slot": "afternoon",
      "day_of_week": "wednesday",
      "got_identified_call": true,
      "phone_number": "+7 (901) 335-66-79"
    },
    {
      "application_id": "APP-1-202",
      "submitted_at": "2026-06-03T20:07:00.000Z",
      "time_slot": "evening",
      "day_of_week": "wednesday",
      "got_identified_call": true,
      "phone_number": "+7 (991) 181-01-99"
    },
    {
      "application_id": "APP-1-236",
      "submitted_at": "2026-06-04T10:27:00.000Z",
      "time_slot": "morning",
      "day_of_week": "thursday",
      "got_identified_call": true,
      "phone_number": "+7 (965) 127-47-13"
    },
    {
      "application_id": "APP-1-270",
      "submitted_at": "2026-06-04T14:23:59.999Z",
      "time_slot": "afternoon",
      "day_of_week": "thursday",
      "got_identified_call": true,
      "phone_number": "+7 (903) 964-17-42"
    },
    {
      "application_id": "APP-1-304",
      "submitted_at": "2026-06-04T20:39:59.999Z",
      "time_slot": "evening",
      "day_of_week": "thursday",
      "got_identified_call": true,
      "phone_number": "+7 (965) 127-09-80"
    },
    {
      "application_id": "APP-1-338",
      "submitted_at": "2026-06-05T09:53:00.000Z",
      "time_slot": "morning",
      "day_of_week": "friday",
      "got_identified_call": true,
      "phone_number": "+7 (903) 673-81-93"
    },
    {
      "application_id": "APP-1-372",
      "submitted_at": "2026-06-05T13:46:00.000Z",
      "time_slot": "afternoon",
      "day_of_week": "friday",
      "got_identified_call": true,
      "phone_number": "+7 (967) 016-79-41"
    },
    {
      "application_id": "APP-1-406",
      "submitted_at": "2026-06-05T20:08:59.999Z",
      "time_slot": "evening",
      "day_of_week": "friday",
      "got_identified_call": true,
      "phone_number": "+7 (903) 586-90-53"
    },
    {
      "application_id": "APP-1-440",
      "submitted_at": "2026-06-06T11:53:59.999Z",
      "time_slot": "morning",
      "day_of_week": "saturday",
      "got_identified_call": true,
      "phone_number": "+7 (903) 791-55-87"
    },
    {
      "application_id": "APP-1-474",
      "submitted_at": "2026-06-06T19:27:00.000Z",
      "time_slot": "afternoon",
      "day_of_week": "saturday",
      "got_identified_call": true,
      "phone_number": "+7 (901) 507-47-17"
    },
    {
      "application_id": "APP-1-508",
      "submitted_at": "2026-06-06T23:11:00.000Z",
      "time_slot": "evening",
      "day_of_week": "saturday",
      "got_identified_call": true,
      "phone_number": "+7 (905) 513-31-09"
    },
    {
      "application_id": "APP-1-542",
      "submitted_at": "2026-06-07T11:34:00.000Z",
      "time_slot": "morning",
      "day_of_week": "sunday",
      "got_identified_call": true,
      "phone_number": "+7 (930) 925-06-25"
    },
    {
      "application_id": "APP-1-576",
      "submitted_at": "2026-06-07T16:50:00.000Z",
      "time_slot": "afternoon",
      "day_of_week": "sunday",
      "got_identified_call": true,
      "phone_number": "+7 (930) 954-93-00"
    },
    {
      "application_id": "APP-1-610",
      "submitted_at": "2026-06-07T00:51:00.000Z",
      "time_slot": "evening",
      "day_of_week": "sunday",
      "got_identified_call": true,
      "phone_number": "+7 (930) 964-06-44"
    },
    {
      "application_id": "APP-1-644",
      "submitted_at": "2026-06-08T11:18:00.000Z",
      "time_slot": "morning",
      "day_of_week": "monday",
      "got_identified_call": true,
      "phone_number": "+7 (901) 347-53-59"
    },
    {
      "application_id": "APP-1-678",
      "submitted_at": "2026-06-08T14:51:00.000Z",
      "time_slot": "afternoon",
      "day_of_week": "monday",
      "got_identified_call": true,
      "phone_number": "+7 (991) 134-10-86"
    },
    {
      "application_id": "APP-1-712",
      "submitted_at": "2026-06-08T23:13:00.000Z",
      "time_slot": "evening",
      "day_of_week": "monday",
      "got_identified_call": false,
      "phone_number": "+7 (991) 238-50-38"
    }
  ],
  "events": [
    {
      "event_id": "E-SC-0510",
      "application_id": "APP-1-032",
      "event_at": "2026-06-02T09:43:00.000Z",
      "minutes_since_application": 133,
      "channel": "call",
      "from_phone": "+7 (863) 310-02-25",
      "identified_status": "developer",
      "verification_confidence": "high"
    },
    {
      "event_id": "events_sms_calls-960",
      "application_id": "",
      "event_at": "2026-06-02T10:57:00.000Z",
      "minutes_since_application": null,
      "channel": "call",
      "from_phone": "+7 (863) 310-02-25",
      "identified_status": "developer",
      "verification_confidence": "high"
    },
    {
      "event_id": "E-SC-0572",
      "application_id": "APP-1-032",
      "event_at": "2026-06-02T13:20:00.000Z",
      "minutes_since_application": 350,
      "channel": "call",
      "from_phone": "+7 (863) 310-02-25",
      "identified_status": "developer",
      "verification_confidence": "high"
    },
    {
      "event_id": "events_sms_calls-1066",
      "application_id": "",
      "event_at": "2026-06-02T15:11:00.000Z",
      "minutes_since_application": null,
      "channel": "call",
      "from_phone": "+7 (863) 310-02-25",
      "identified_status": "developer",
      "verification_confidence": "high"
    },
    {
      "event_id": "events_sms_calls-1175",
      "application_id": "",
      "event_at": "03.06.2026 9:28",
      "minutes_since_application": null,
      "channel": "call",
      "from_phone": "+7 (863) 310-02-25",
      "identified_status": "developer",
      "verification_confidence": "high"
    },
    {
      "event_id": "E-SC-0663",
      "application_id": "APP-1-100",
      "event_at": "2026-06-03T07:23:00.000Z",
      "minutes_since_application": 708,
      "channel": "call",
      "from_phone": "+7 (863) 310-02-25",
      "identified_status": "developer",
      "verification_confidence": "high"
    },
    {
      "event_id": "E-SC-0720",
      "application_id": "APP-1-134",
      "event_at": "2026-06-03T09:34:00.000Z",
      "minutes_since_application": 139,
      "channel": "call",
      "from_phone": "+7 (863) 310-02-25",
      "identified_status": "developer",
      "verification_confidence": "high"
    },
    {
      "event_id": "E-SC-0766",
      "application_id": "APP-1-100",
      "event_at": "2026-06-03T10:42:00.000Z",
      "minutes_since_application": 907,
      "channel": "call",
      "from_phone": "+7 (863) 310-02-25",
      "identified_status": "developer",
      "verification_confidence": "high"
    },
    {
      "event_id": "E-SC-0820",
      "application_id": "APP-1-168",
      "event_at": "2026-06-03T11:38:00.000Z",
      "minutes_since_application": 1,
      "channel": "call",
      "from_phone": "+7 (863) 310-02-25",
      "identified_status": "developer",
      "verification_confidence": "high"
    },
    {
      "event_id": "E-SC-0861",
      "application_id": "APP-1-168",
      "event_at": "2026-06-03T13:04:00.000Z",
      "minutes_since_application": 87,
      "channel": "call",
      "from_phone": "+7 (863) 310-02-25",
      "identified_status": "developer",
      "verification_confidence": "high"
    },
    {
      "event_id": "E-SC-0893",
      "application_id": "APP-1-168",
      "event_at": "2026-06-03T15:24:00.000Z",
      "minutes_since_application": 227,
      "channel": "call",
      "from_phone": "+7 (863) 310-02-25",
      "identified_status": "developer",
      "verification_confidence": "high"
    },
    {
      "event_id": "E-SC-1052",
      "application_id": "APP-1-202",
      "event_at": "2026-06-04T07:30:00.000Z",
      "minutes_since_application": 863,
      "channel": "call",
      "from_phone": "+7 (863) 310-02-25",
      "identified_status": "developer",
      "verification_confidence": "high"
    },
    {
      "event_id": "E-SC-1105",
      "application_id": "APP-1-236",
      "event_at": "2026-06-04T08:36:00.000Z",
      "minutes_since_application": 69,
      "channel": "call",
      "from_phone": "+7 (863) 310-02-25",
      "identified_status": "developer",
      "verification_confidence": "high"
    },
    {
      "event_id": "E-SC-1155",
      "application_id": "APP-1-236",
      "event_at": "2026-06-04T10:11:00.000Z",
      "minutes_since_application": 164,
      "channel": "call",
      "from_phone": "+7 (863) 310-02-25",
      "identified_status": "developer",
      "verification_confidence": "high"
    },
    {
      "event_id": "E-SC-1156",
      "application_id": "APP-1-202",
      "event_at": "2026-06-04T10:12:00.000Z",
      "minutes_since_application": 1025,
      "channel": "call",
      "from_phone": "+7 (863) 310-02-25",
      "identified_status": "developer",
      "verification_confidence": "high"
    },
    {
      "event_id": "E-SC-1158",
      "application_id": "APP-1-066",
      "event_at": "2026-06-04T10:14:00.000Z",
      "minutes_since_application": 2844,
      "channel": "call",
      "from_phone": "+7 (863) 310-02-25",
      "identified_status": "developer",
      "verification_confidence": "high"
    },
    {
      "event_id": "E-SC-1160",
      "application_id": "APP-1-032",
      "event_at": "2026-06-04T10:17:00.000Z",
      "minutes_since_application": 3047,
      "channel": "call",
      "from_phone": "+7 (863) 310-02-25",
      "identified_status": "developer",
      "verification_confidence": "high"
    },
    {
      "event_id": "E-SC-1345",
      "application_id": "APP-1-270",
      "event_at": "2026-06-04T16:09:00.000Z",
      "minutes_since_application": 285,
      "channel": "call",
      "from_phone": "+7 (863) 310-02-25",
      "identified_status": "developer",
      "verification_confidence": "high"
    },
    {
      "event_id": "E-SC-1420",
      "application_id": "APP-1-304",
      "event_at": "05.06.2026 9:16",
      "minutes_since_application": 756,
      "channel": "call",
      "from_phone": "+7 (863) 310-02-25",
      "identified_status": "developer",
      "verification_confidence": "high"
    },
    {
      "event_id": "E-SC-1550",
      "application_id": "APP-1-304",
      "event_at": "2026-06-05T07:58:00.000Z",
      "minutes_since_application": 858,
      "channel": "call",
      "from_phone": "+7 (863) 310-02-25",
      "identified_status": "developer",
      "verification_confidence": "high"
    },
    {
      "event_id": "E-SC-1661",
      "application_id": "APP-1-066",
      "event_at": "2026-06-05T10:46:00.000Z",
      "minutes_since_application": 4316,
      "channel": "call",
      "from_phone": "+7 (863) 310-02-25",
      "identified_status": "developer",
      "verification_confidence": "high"
    },
    {
      "event_id": "E-SC-1662",
      "application_id": "APP-1-304",
      "event_at": "2026-06-05T10:47:00.000Z",
      "minutes_since_application": 1027,
      "channel": "call",
      "from_phone": "+7 (863) 310-02-25",
      "identified_status": "developer",
      "verification_confidence": "high"
    },
    {
      "event_id": "events_sms_calls-3104",
      "application_id": "",
      "event_at": "2026-06-05T12:12:00.000Z",
      "minutes_since_application": null,
      "channel": "call",
      "from_phone": "+7 (863) 310-02-25",
      "identified_status": "developer",
      "verification_confidence": "high"
    },
    {
      "event_id": "E-SC-1757",
      "application_id": "APP-1-270",
      "event_at": "2026-06-05T14:00:00.000Z",
      "minutes_since_application": 1596,
      "channel": "call",
      "from_phone": "+7 (863) 310-02-25",
      "identified_status": "developer",
      "verification_confidence": "high"
    },
    {
      "event_id": "events_sms_calls-3256",
      "application_id": "",
      "event_at": "2026-06-05T14:38:00.000Z",
      "minutes_since_application": null,
      "channel": "call",
      "from_phone": "+7 (863) 310-02-25",
      "identified_status": "developer",
      "verification_confidence": "high"
    },
    {
      "event_id": "E-SC-1815",
      "application_id": "APP-1-406",
      "event_at": "06.06.2026 9:31",
      "minutes_since_application": 802,
      "channel": "call",
      "from_phone": "+7 (863) 310-02-25",
      "identified_status": "developer",
      "verification_confidence": "high"
    },
    {
      "event_id": "E-SC-1897",
      "application_id": "APP-1-304",
      "event_at": "2026-06-06T08:09:00.000Z",
      "minutes_since_application": 2309,
      "channel": "call",
      "from_phone": "+7 (863) 310-02-25",
      "identified_status": "developer",
      "verification_confidence": "high"
    },
    {
      "event_id": "E-SC-1904",
      "application_id": "APP-1-338",
      "event_at": "2026-06-06T08:14:00.000Z",
      "minutes_since_application": 1521,
      "channel": "call",
      "from_phone": "+7 (863) 310-02-25",
      "identified_status": "developer",
      "verification_confidence": "high"
    },
    {
      "event_id": "events_sms_calls-3559",
      "application_id": "",
      "event_at": "2026-06-06T08:16:00.000Z",
      "minutes_since_application": null,
      "channel": "call",
      "from_phone": "+7 (863) 310-02-25",
      "identified_status": "developer",
      "verification_confidence": "high"
    },
    {
      "event_id": "events_sms_calls-3619",
      "application_id": "",
      "event_at": "2026-06-06T08:58:00.000Z",
      "minutes_since_application": null,
      "channel": "call",
      "from_phone": "+7 (863) 310-02-25",
      "identified_status": "developer",
      "verification_confidence": "high"
    },
    {
      "event_id": "events_sms_calls-3655",
      "application_id": "",
      "event_at": "2026-06-06T09:27:00.000Z",
      "minutes_since_application": null,
      "channel": "call",
      "from_phone": "+7 (863) 310-02-25",
      "identified_status": "developer",
      "verification_confidence": "high"
    },
    {
      "event_id": "events_sms_calls-3658",
      "application_id": "",
      "event_at": "2026-06-06T09:29:00.000Z",
      "minutes_since_application": null,
      "channel": "call",
      "from_phone": "+7 (863) 310-02-25",
      "identified_status": "developer",
      "verification_confidence": "high"
    },
    {
      "event_id": "E-SC-1950",
      "application_id": "APP-1-168",
      "event_at": "2026-06-06T09:30:00.000Z",
      "minutes_since_application": 4193,
      "channel": "call",
      "from_phone": "+7 (863) 310-02-25",
      "identified_status": "developer",
      "verification_confidence": "high"
    },
    {
      "event_id": "E-SC-1951",
      "application_id": "APP-1-406",
      "event_at": "2026-06-06T09:31:00.000Z",
      "minutes_since_application": 982,
      "channel": "call",
      "from_phone": "+7 (863) 310-02-25",
      "identified_status": "developer",
      "verification_confidence": "high"
    },
    {
      "event_id": "events_sms_calls-3663",
      "application_id": "",
      "event_at": "2026-06-06T09:33:00.000Z",
      "minutes_since_application": null,
      "channel": "call",
      "from_phone": "+7 (863) 310-02-25",
      "identified_status": "developer",
      "verification_confidence": "high"
    },
    {
      "event_id": "E-SC-1969",
      "application_id": "APP-1-406",
      "event_at": "2026-06-06T10:45:00.000Z",
      "minutes_since_application": 1056,
      "channel": "call",
      "from_phone": "+7 (863) 310-02-25",
      "identified_status": "developer",
      "verification_confidence": "high"
    },
    {
      "event_id": "events_sms_calls-3743",
      "application_id": "",
      "event_at": "2026-06-06T10:49:00.000Z",
      "minutes_since_application": null,
      "channel": "call",
      "from_phone": "+7 (863) 310-02-25",
      "identified_status": "developer",
      "verification_confidence": "high"
    },
    {
      "event_id": "events_sms_calls-3993",
      "application_id": "",
      "event_at": "07.06.2026 8:23",
      "minutes_since_application": null,
      "channel": "call",
      "from_phone": "+7 (343) 304-64-34",
      "identified_status": "developer",
      "verification_confidence": "high"
    },
    {
      "event_id": "E-SC-2065",
      "application_id": "APP-1-440",
      "event_at": "07.06.2026 8:25",
      "minutes_since_application": 1231,
      "channel": "call",
      "from_phone": "+7 (343) 304-64-34",
      "identified_status": "developer",
      "verification_confidence": "high"
    },
    {
      "event_id": "events_sms_calls-3999",
      "application_id": "",
      "event_at": "07.06.2026 8:42",
      "minutes_since_application": null,
      "channel": "call",
      "from_phone": "+7 (343) 304-64-34",
      "identified_status": "developer",
      "verification_confidence": "high"
    },
    {
      "event_id": "events_sms_calls-4134",
      "application_id": "",
      "event_at": "2026-06-07T07:59:00.000Z",
      "minutes_since_application": null,
      "channel": "call",
      "from_phone": "+7 (863) 310-02-25",
      "identified_status": "developer",
      "verification_confidence": "high"
    },
    {
      "event_id": "events_sms_calls-4141",
      "application_id": "",
      "event_at": "2026-06-07T08:02:00.000Z",
      "minutes_since_application": null,
      "channel": "call",
      "from_phone": "+7 (863) 310-02-25",
      "identified_status": "developer",
      "verification_confidence": "high"
    },
    {
      "event_id": "events_sms_calls-4142",
      "application_id": "",
      "event_at": "2026-06-07T08:02:00.000Z",
      "minutes_since_application": null,
      "channel": "call",
      "from_phone": "+7 (863) 310-02-25",
      "identified_status": "developer",
      "verification_confidence": "high"
    },
    {
      "event_id": "E-SC-2135",
      "application_id": "APP-1-508",
      "event_at": "2026-06-07T08:05:00.000Z",
      "minutes_since_application": 714,
      "channel": "call",
      "from_phone": "+7 (863) 310-02-25",
      "identified_status": "developer",
      "verification_confidence": "high"
    },
    {
      "event_id": "E-SC-2172",
      "application_id": "APP-1-474",
      "event_at": "2026-06-07T08:44:00.000Z",
      "minutes_since_application": 977,
      "channel": "call",
      "from_phone": "+7 (343) 304-64-34",
      "identified_status": "developer",
      "verification_confidence": "high"
    },
    {
      "event_id": "events_sms_calls-4466",
      "application_id": "",
      "event_at": "2026-06-07T13:31:00.000Z",
      "minutes_since_application": null,
      "channel": "call",
      "from_phone": "+7 (863) 310-02-25",
      "identified_status": "developer",
      "verification_confidence": "high"
    },
    {
      "event_id": "E-SC-2370",
      "application_id": "APP-1-610",
      "event_at": "08.06.2026 7:05",
      "minutes_since_application": 1814,
      "channel": "call",
      "from_phone": "+7 (343) 304-64-34",
      "identified_status": "developer",
      "verification_confidence": "high"
    },
    {
      "event_id": "E-SC-2372",
      "application_id": "APP-1-576",
      "event_at": "08.06.2026 7:11",
      "minutes_since_application": 861,
      "channel": "call",
      "from_phone": "+7 (343) 304-64-34",
      "identified_status": "developer",
      "verification_confidence": "high"
    },
    {
      "event_id": "E-SC-2446",
      "application_id": "APP-1-474",
      "event_at": "08.06.2026 9:20",
      "minutes_since_application": 2273,
      "channel": "call",
      "from_phone": "+7 (343) 304-64-34",
      "identified_status": "developer",
      "verification_confidence": "high"
    },
    {
      "event_id": "E-SC-2453",
      "application_id": "APP-1-440",
      "event_at": "08.06.2026 9:23",
      "minutes_since_application": 2729,
      "channel": "call",
      "from_phone": "+7 (343) 304-64-34",
      "identified_status": "developer",
      "verification_confidence": "high"
    },
    {
      "event_id": "events_sms_calls-4864",
      "application_id": "",
      "event_at": "2026-06-08T07:29:00.000Z",
      "minutes_since_application": null,
      "channel": "call",
      "from_phone": "+7 (863) 310-02-25",
      "identified_status": "developer",
      "verification_confidence": "high"
    },
    {
      "event_id": "events_sms_calls-4867",
      "application_id": "",
      "event_at": "2026-06-08T07:30:00.000Z",
      "minutes_since_application": null,
      "channel": "call",
      "from_phone": "+7 (863) 310-02-25",
      "identified_status": "developer",
      "verification_confidence": "high"
    },
    {
      "event_id": "events_sms_calls-4873",
      "application_id": "",
      "event_at": "2026-06-08T07:32:00.000Z",
      "minutes_since_application": null,
      "channel": "call",
      "from_phone": "+7 (863) 310-02-25",
      "identified_status": "developer",
      "verification_confidence": "high"
    },
    {
      "event_id": "E-SC-2562",
      "application_id": "APP-1-644",
      "event_at": "2026-06-08T08:19:00.000Z",
      "minutes_since_application": 1,
      "channel": "call",
      "from_phone": "+7 (343) 304-64-34",
      "identified_status": "developer",
      "verification_confidence": "high"
    },
    {
      "event_id": "events_sms_calls-5089",
      "application_id": "",
      "event_at": "2026-06-08T10:03:00.000Z",
      "minutes_since_application": null,
      "channel": "call",
      "from_phone": "+7 (863) 310-02-25",
      "identified_status": "developer",
      "verification_confidence": "high"
    },
    {
      "event_id": "events_sms_calls-5091",
      "application_id": "",
      "event_at": "2026-06-08T10:04:00.000Z",
      "minutes_since_application": null,
      "channel": "call",
      "from_phone": "+7 (863) 310-02-25",
      "identified_status": "developer",
      "verification_confidence": "high"
    },
    {
      "event_id": "E-SC-2645",
      "application_id": "APP-1-372",
      "event_at": "2026-06-08T10:06:00.000Z",
      "minutes_since_application": 4280,
      "channel": "call",
      "from_phone": "+7 (863) 310-02-25",
      "identified_status": "developer",
      "verification_confidence": "high"
    },
    {
      "event_id": "E-SC-2724",
      "application_id": "APP-1-678",
      "event_at": "2026-06-08T11:52:00.000Z",
      "minutes_since_application": 1,
      "channel": "call",
      "from_phone": "+7 (343) 304-64-34",
      "identified_status": "developer",
      "verification_confidence": "high"
    },
    {
      "event_id": "E-SC-2730",
      "application_id": "APP-1-542",
      "event_at": "2026-06-08T11:57:00.000Z",
      "minutes_since_application": 1643,
      "channel": "call",
      "from_phone": "+7 (343) 304-64-34",
      "identified_status": "developer",
      "verification_confidence": "high"
    },
    {
      "event_id": "events_sms_calls-5660",
      "application_id": "",
      "event_at": "09.06.2026 7:08",
      "minutes_since_application": null,
      "channel": "call",
      "from_phone": "+7 (343) 304-64-34",
      "identified_status": "developer",
      "verification_confidence": "high"
    },
    {
      "event_id": "E-SC-2862",
      "application_id": "APP-1-576",
      "event_at": "09.06.2026 9:14",
      "minutes_since_application": 2424,
      "channel": "call",
      "from_phone": "+7 (343) 304-64-34",
      "identified_status": "developer",
      "verification_confidence": "high"
    },
    {
      "event_id": "events_sms_calls-5780",
      "application_id": "",
      "event_at": "2026-06-09T07:58:00.000Z",
      "minutes_since_application": null,
      "channel": "call",
      "from_phone": "+7 (863) 310-02-25",
      "identified_status": "developer",
      "verification_confidence": "high"
    },
    {
      "event_id": "events_sms_calls-5782",
      "application_id": "",
      "event_at": "2026-06-09T07:59:00.000Z",
      "minutes_since_application": null,
      "channel": "call",
      "from_phone": "+7 (863) 310-02-25",
      "identified_status": "developer",
      "verification_confidence": "high"
    },
    {
      "event_id": "events_sms_calls-5816",
      "application_id": "",
      "event_at": "2026-06-09T08:30:00.000Z",
      "minutes_since_application": null,
      "channel": "call",
      "from_phone": "+7 (863) 310-02-25",
      "identified_status": "developer",
      "verification_confidence": "high"
    },
    {
      "event_id": "events_sms_calls-5848",
      "application_id": "",
      "event_at": "2026-06-09T09:16:00.000Z",
      "minutes_since_application": null,
      "channel": "call",
      "from_phone": "+7 (863) 310-02-25",
      "identified_status": "developer",
      "verification_confidence": "high"
    },
    {
      "event_id": "events_sms_calls-5852",
      "application_id": "",
      "event_at": "2026-06-09T09:17:00.000Z",
      "minutes_since_application": null,
      "channel": "call",
      "from_phone": "+7 (863) 310-02-25",
      "identified_status": "developer",
      "verification_confidence": "high"
    },
    {
      "event_id": "events_sms_calls-5858",
      "application_id": "",
      "event_at": "2026-06-09T09:19:00.000Z",
      "minutes_since_application": null,
      "channel": "call",
      "from_phone": "+7 (863) 310-02-25",
      "identified_status": "developer",
      "verification_confidence": "high"
    },
    {
      "event_id": "E-SC-2919",
      "application_id": "APP-1-610",
      "event_at": "2026-06-09T12:06:00.000Z",
      "minutes_since_application": 3735,
      "channel": "call",
      "from_phone": "+7 (343) 304-64-34",
      "identified_status": "developer",
      "verification_confidence": "high"
    },
    {
      "event_id": "events_sms_calls-6260",
      "application_id": "",
      "event_at": "10.06.2026 7:39",
      "minutes_since_application": null,
      "channel": "call",
      "from_phone": "+7 (343) 304-64-34",
      "identified_status": "developer",
      "verification_confidence": "high"
    },
    {
      "event_id": "E-SC-2953",
      "application_id": "APP-1-678",
      "event_at": "10.06.2026 7:44",
      "minutes_since_application": 2453,
      "channel": "call",
      "from_phone": "+7 (343) 304-64-34",
      "identified_status": "developer",
      "verification_confidence": "high"
    },
    {
      "event_id": "E-SC-2959",
      "application_id": "APP-1-542",
      "event_at": "10.06.2026 9:14",
      "minutes_since_application": 4180,
      "channel": "call",
      "from_phone": "+7 (343) 304-64-34",
      "identified_status": "developer",
      "verification_confidence": "high"
    },
    {
      "event_id": "E-SC-2960",
      "application_id": "APP-1-644",
      "event_at": "10.06.2026 9:14",
      "minutes_since_application": 2756,
      "channel": "call",
      "from_phone": "+7 (343) 304-64-34",
      "identified_status": "developer",
      "verification_confidence": "high"
    },
    {
      "event_id": "events_sms_calls-6293",
      "application_id": "",
      "event_at": "10.06.2026 9:16",
      "minutes_since_application": null,
      "channel": "call",
      "from_phone": "+7 (343) 304-64-34",
      "identified_status": "developer",
      "verification_confidence": "high"
    },
    {
      "event_id": "events_sms_calls-6299",
      "application_id": "",
      "event_at": "10.06.2026 9:22",
      "minutes_since_application": null,
      "channel": "call",
      "from_phone": "+7 (343) 304-64-34",
      "identified_status": "developer",
      "verification_confidence": "high"
    },
    {
      "event_id": "E-SC-2965",
      "application_id": "APP-1-576",
      "event_at": "10.06.2026 9:27",
      "minutes_since_application": 3877,
      "channel": "call",
      "from_phone": "+7 (343) 304-64-34",
      "identified_status": "developer",
      "verification_confidence": "high"
    },
    {
      "event_id": "events_sms_calls-6448",
      "application_id": "",
      "event_at": "2026-06-10T08:57:00.000Z",
      "minutes_since_application": null,
      "channel": "call",
      "from_phone": "+7 (863) 310-02-25",
      "identified_status": "developer",
      "verification_confidence": "high"
    },
    {
      "event_id": "events_sms_calls-6451",
      "application_id": "",
      "event_at": "2026-06-10T09:01:00.000Z",
      "minutes_since_application": null,
      "channel": "call",
      "from_phone": "+7 (863) 310-02-25",
      "identified_status": "developer",
      "verification_confidence": "high"
    },
    {
      "event_id": "events_sms_calls-6455",
      "application_id": "",
      "event_at": "2026-06-10T09:03:00.000Z",
      "minutes_since_application": null,
      "channel": "call",
      "from_phone": "+7 (863) 310-02-25",
      "identified_status": "developer",
      "verification_confidence": "high"
    },
    {
      "event_id": "events_sms_calls-6457",
      "application_id": "",
      "event_at": "2026-06-10T09:05:00.000Z",
      "minutes_since_application": null,
      "channel": "call",
      "from_phone": "+7 (863) 310-02-25",
      "identified_status": "developer",
      "verification_confidence": "high"
    },
    {
      "event_id": "events_sms_calls-6459",
      "application_id": "",
      "event_at": "2026-06-10T09:08:00.000Z",
      "minutes_since_application": null,
      "channel": "call",
      "from_phone": "+7 (863) 310-02-25",
      "identified_status": "developer",
      "verification_confidence": "high"
    },
    {
      "event_id": "events_sms_calls-6462",
      "application_id": "",
      "event_at": "2026-06-10T09:09:00.000Z",
      "minutes_since_application": null,
      "channel": "call",
      "from_phone": "+7 (863) 310-02-25",
      "identified_status": "developer",
      "verification_confidence": "high"
    },
    {
      "event_id": "events_sms_calls-6464",
      "application_id": "",
      "event_at": "2026-06-10T09:10:00.000Z",
      "minutes_since_application": null,
      "channel": "call",
      "from_phone": "+7 (863) 310-02-25",
      "identified_status": "developer",
      "verification_confidence": "high"
    },
    {
      "event_id": "events_sms_calls-6467",
      "application_id": "",
      "event_at": "2026-06-10T09:12:00.000Z",
      "minutes_since_application": null,
      "channel": "call",
      "from_phone": "+7 (863) 310-02-25",
      "identified_status": "developer",
      "verification_confidence": "high"
    },
    {
      "event_id": "events_sms_calls-6935",
      "application_id": "",
      "event_at": "11.06.2026 9:12",
      "minutes_since_application": null,
      "channel": "call",
      "from_phone": "+7 (343) 304-64-34",
      "identified_status": "developer",
      "verification_confidence": "high"
    },
    {
      "event_id": "events_sms_calls-6936",
      "application_id": "",
      "event_at": "11.06.2026 9:13",
      "minutes_since_application": null,
      "channel": "call",
      "from_phone": "+7 (343) 304-64-34",
      "identified_status": "developer",
      "verification_confidence": "high"
    },
    {
      "event_id": "E-SC-3028",
      "application_id": "APP-1-644",
      "event_at": "11.06.2026 9:28",
      "minutes_since_application": 4210,
      "channel": "call",
      "from_phone": "+7 (343) 304-64-34",
      "identified_status": "developer",
      "verification_confidence": "high"
    },
    {
      "event_id": "events_sms_calls-6951",
      "application_id": "",
      "event_at": "11.06.2026 9:34",
      "minutes_since_application": null,
      "channel": "call",
      "from_phone": "+7 (343) 304-64-34",
      "identified_status": "developer",
      "verification_confidence": "high"
    },
    {
      "event_id": "E-SC-3029",
      "application_id": "APP-1-678",
      "event_at": "11.06.2026 9:36",
      "minutes_since_application": 4005,
      "channel": "call",
      "from_phone": "+7 (343) 304-64-34",
      "identified_status": "developer",
      "verification_confidence": "high"
    },
    {
      "event_id": "events_sms_calls-7105",
      "application_id": "",
      "event_at": "2026-06-11T09:16:00.000Z",
      "minutes_since_application": null,
      "channel": "call",
      "from_phone": "+7 (863) 310-02-25",
      "identified_status": "developer",
      "verification_confidence": "high"
    },
    {
      "event_id": "events_sms_calls-7106",
      "application_id": "",
      "event_at": "2026-06-11T09:17:00.000Z",
      "minutes_since_application": null,
      "channel": "call",
      "from_phone": "+7 (863) 310-02-25",
      "identified_status": "developer",
      "verification_confidence": "high"
    },
    {
      "event_id": "events_sms_calls-7182",
      "application_id": "",
      "event_at": "2026-06-11T11:12:00.000Z",
      "minutes_since_application": null,
      "channel": "call",
      "from_phone": "+7 (343) 304-64-34",
      "identified_status": "developer",
      "verification_confidence": "high"
    },
    {
      "event_id": "events_sms_calls-7183",
      "application_id": "",
      "event_at": "2026-06-11T11:13:00.000Z",
      "minutes_since_application": null,
      "channel": "call",
      "from_phone": "+7 (343) 304-64-34",
      "identified_status": "developer",
      "verification_confidence": "high"
    },
    {
      "event_id": "events_sms_calls-7246",
      "application_id": "",
      "event_at": "2026-06-11T12:32:00.000Z",
      "minutes_since_application": null,
      "channel": "call",
      "from_phone": "+7 (863) 310-02-25",
      "identified_status": "developer",
      "verification_confidence": "high"
    },
    {
      "event_id": "events_sms_calls-7439",
      "application_id": "",
      "event_at": "12.06.2026 8:45",
      "minutes_since_application": null,
      "channel": "call",
      "from_phone": "+7 (343) 304-64-34",
      "identified_status": "developer",
      "verification_confidence": "high"
    },
    {
      "event_id": "events_sms_calls-7440",
      "application_id": "",
      "event_at": "12.06.2026 8:46",
      "minutes_since_application": null,
      "channel": "call",
      "from_phone": "+7 (343) 304-64-34",
      "identified_status": "developer",
      "verification_confidence": "high"
    },
    {
      "event_id": "events_sms_calls-7441",
      "application_id": "",
      "event_at": "12.06.2026 8:47",
      "minutes_since_application": null,
      "channel": "call",
      "from_phone": "+7 (343) 304-64-34",
      "identified_status": "developer",
      "verification_confidence": "high"
    },
    {
      "event_id": "events_sms_calls-7442",
      "application_id": "",
      "event_at": "12.06.2026 8:50",
      "minutes_since_application": null,
      "channel": "call",
      "from_phone": "+7 (343) 304-64-34",
      "identified_status": "developer",
      "verification_confidence": "high"
    },
    {
      "event_id": "events_sms_calls-7443",
      "application_id": "",
      "event_at": "12.06.2026 8:53",
      "minutes_since_application": null,
      "channel": "call",
      "from_phone": "+7 (343) 304-64-34",
      "identified_status": "developer",
      "verification_confidence": "high"
    },
    {
      "event_id": "events_sms_calls-7543",
      "application_id": "",
      "event_at": "2026-06-12T10:33:00.000Z",
      "minutes_since_application": null,
      "channel": "call",
      "from_phone": "+7 (863) 310-02-25",
      "identified_status": "developer",
      "verification_confidence": "high"
    },
    {
      "event_id": "events_sms_calls-7545",
      "application_id": "",
      "event_at": "2026-06-12T10:35:00.000Z",
      "minutes_since_application": null,
      "channel": "call",
      "from_phone": "+7 (863) 310-02-25",
      "identified_status": "developer",
      "verification_confidence": "high"
    }
  ]
}
